leaf_diag-0.1.3.dist-info/METADATA
leaf_diag-0.1.3.dist-info/WHEEL
leaf_diag-0.1.3.dist-info/entry_points.txt
leaf_diag/__init__.py
leaf_diag/data_loader.py
leaf_diag/data_sync.py
leaf_diag/data_transform.py
leaf_diag/ros_utils.py
leaf_diag/ulog_export.py
leaf_diag-0.1.3.dist-info/RECORD
