Metadata-Version: 2.1
Name: leaf-diag
Version: 0.1.3
Summary: A diagnostic tool for parsing DroneLeaf controller and PX4 logs
Author-Email: Khalil Al Handawi <khalil.alhandawi@mail.mcgill.ca>
License: MIT
Requires-Python: <3.12,>=3.9
Requires-Dist: bagpy>=0.5
Requires-Dist: px4tools>=0.9.6
Requires-Dist: tqdm>=4.67.1
Requires-Dist: scipy>=1.9.3
Requires-Dist: numpy>=1.24.4
Requires-Dist: pydantic>=2.12.5
